[
{"id":"batman","head":{"x":6,"y":59},"chest":{"x":6,"y":24},"actions":{"wait":{"x":0.51,"y":0.36,"rate":10},"run":{"x":0.51,"y":0.36,"rate":24},"attack":{"x":0.51,"y":0.36,"rate":24,"a":3,"b":0},"magic":{"x":0.51,"y":0.36,"rate":12,"a":6,"b":0},"magic2":{"x":0.51,"y":0.36,"rate":20,"a":6,"b":0},"magic3":{"x":0.51,"y":0.36,"rate":20,"a":6,"b":0},"dead":{"x":0.51,"y":0.36,"rate":16},"faint":{"x":0.51,"y":0.36,"rate":15},"passive":{"x":0.51,"y":0.36,"rate":10,"a":7,"b":0},"win1":{"x":0.51,"y":0.36,"rate":12},"win2":{"x":0.51,"y":0.36,"rate":12}},"runSound":"run","runSoundSpeed":333.3333333333333,"deadSound":"run","sex":1},
{"id":"tetsuo","head":{"x":6,"y":59},"chest":{"x":6,"y":24},"actions":{"wait":{"x":0.51,"y":0.36,"rate":10},"run":{"x":0.51,"y":0.36,"rate":24},"attack":{"x":0.51,"y":0.36,"rate":24,"a":5,"b":0},"magic":{"x":0.51,"y":0.36,"rate":15,"a":1,"b":0},"magic2":{"x":0.51,"y":0.36,"rate":10,"a":17,"b":0},"magic3":{"x":0.51,"y":0.36,"rate":10,"a":17,"b":0},"dead":{"x":0.51,"y":0.36,"rate":16},"faint":{"x":0.51,"y":0.36,"rate":15},"passive":{"x":0.51,"y":0.36,"rate":10,"a":7,"b":0},"win1":{"x":0.51,"y":0.36,"rate":12},"win2":{"x":0.51,"y":0.36,"rate":12}},"runSound":"run","runSoundSpeed":333.3333333333333,"deadSound":"run","sex":1},
{"id":"tetsuo2","head":{"x":6,"y":59},"chest":{"x":6,"y":24},"actions":{"wait":{"x":0.51,"y":0.36,"rate":10},"run":{"x":0.51,"y":0.36,"rate":24},"attack":{"x":0.51,"y":0.36,"rate":24,"a":5,"b":0},"magic":{"x":0.51,"y":0.36,"rate":20,"a":4,"b":0},"magic2":{"x":0.51,"y":0.36,"rate":20,"a":4,"b":0},"magic3":{"x":0.51,"y":0.36,"rate":20,"a":4,"b":0},"dead":{"x":0.51,"y":0.36,"rate":16},"faint":{"x":0.51,"y":0.36,"rate":15},"passive":{"x":0.51,"y":0.36,"rate":10,"a":7,"b":0},"win1":{"x":0.51,"y":0.36,"rate":12},"win2":{"x":0.51,"y":0.36,"rate":12}},"runSound":"run","runSoundSpeed":333.3333333333333,"deadSound":"run","sex":1},
{"id":"whalegirl","head":{"x":6,"y":59},"chest":{"x":6,"y":24},"actions":{"wait":{"x":0.51,"y":0.36,"rate":10},"run":{"x":0.51,"y":0.36,"rate":24},"attack":{"x":0.51,"y":0.36,"rate":16,"a":4,"b":0},"magic":{"x":0.51,"y":0.36,"rate":10,"a":6,"b":0},"magic2":{"x":0.51,"y":0.36,"rate":10,"a":6,"b":0},"magic3":{"x":0.51,"y":0.36,"rate":10,"a":6,"b":0},"dead":{"x":0.51,"y":0.36,"rate":16},"faint":{"x":0.51,"y":0.36,"rate":15},"passive":{"x":0.51,"y":0.36,"rate":10,"a":7,"b":0},"win1":{"x":0.51,"y":0.36,"rate":12},"win2":{"x":0.51,"y":0.36,"rate":12}},"runSound":"run","runSoundSpeed":333.3333333333333,"deadSound":"run","sex":1},
{"id":"ryu","head":{"x":0,"y":72},"chest":{"x":6,"y":24},"actions":{"wait":{"x":0.51,"y":0.36,"rate":10},"run":{"x":0.51,"y":0.36,"rate":24},"attack":{"x":0.51,"y":0.36,"rate":24,"a":5,"b":0},"magic":{"x":0.51,"y":0.36,"rate":10,"a":5,"b":0},"magic2":{"x":0.51,"y":0.36,"rate":20,"a":5,"b":0},"magic3":{"x":0.51,"y":0.36,"rate":20,"a":5,"b":0},"dead":{"x":0.51,"y":0.36,"rate":16},"faint":{"x":0.51,"y":0.36,"rate":15},"passive":{"x":0.51,"y":0.36,"rate":36,"a":11,"b":0},"win1":{"x":0.51,"y":0.36,"rate":12},"win2":{"x":0.51,"y":0.36,"rate":12}},"runSound":"run","runSoundSpeed":333.3333333333333,"deadSound":"run","sex":1},
{"id":"legolas","head":{"x":6,"y":59},"chest":{"x":6,"y":24},"actions":{"wait":{"x":0.51,"y":0.36,"rate":10},"run":{"x":0.51,"y":0.36,"rate":24},"attack":{"x":0.51,"y":0.36,"rate":24,"a":2,"b":0},"magic":{"x":0.51,"y":0.36,"rate":10,"a":2,"b":0},"magic2":{"x":0.51,"y":0.36,"rate":20,"a":2,"b":0},"magic3":{"x":0.51,"y":0.36,"rate":20,"a":2,"b":0},"dead":{"x":0.51,"y":0.36,"rate":16},"faint":{"x":0.51,"y":0.36,"rate":15},"passive":{"x":0.51,"y":0.36,"rate":15,"a":5,"b":0},"win1":{"x":0.51,"y":0.36,"rate":12},"win2":{"x":0.51,"y":0.36,"rate":12}},"runSound":"run","runSoundSpeed":333.3333333333333,"deadSound":"run","sex":1},
{"id":"redman","head":{"x":0,"y":59},"chest":{"x":6,"y":24},"actions":{"wait":{"x":0.51,"y":0.36,"rate":10},"run":{"x":0.51,"y":0.36,"rate":24},"attack":{"x":0.51,"y":0.36,"rate":18,"a":3,"b":0},"magic":{"x":0.51,"y":0.36,"rate":10,"a":4,"b":0},"magic2":{"x":0.51,"y":0.36,"rate":20,"a":4,"b":0},"magic3":{"x":0.51,"y":0.36,"rate":20,"a":4,"b":0},"dead":{"x":0.51,"y":0.36,"rate":16},"faint":{"x":0.51,"y":0.36,"rate":15},"passive":{"x":0.51,"y":0.36,"rate":15,"a":5,"b":0},"win1":{"x":0.51,"y":0.36,"rate":12},"win2":{"x":0.51,"y":0.36,"rate":12}},"runSound":"run","runSoundSpeed":333.3333333333333,"deadSound":"run","sex":1},
{"id":"superwoman","head":{"x":6,"y":59},"chest":{"x":6,"y":24},"actions":{"wait":{"x":0.51,"y":0.36,"rate":10},"run":{"x":0.51,"y":0.36,"rate":24},"attack":{"x":0.51,"y":0.36,"rate":22,"a":4,"b":0},"magic":{"x":0.51,"y":0.36,"rate":10,"a":5,"b":0},"magic2":{"x":0.51,"y":0.36,"rate":20,"a":5,"b":0},"magic3":{"x":0.51,"y":0.36,"rate":20,"a":7,"b":0},"dead":{"x":0.51,"y":0.36,"rate":16},"faint":{"x":0.51,"y":0.36,"rate":15},"passive":{"x":0.51,"y":0.36,"rate":10,"a":7,"b":0},"win1":{"x":0.51,"y":0.36,"rate":12},"win2":{"x":0.51,"y":0.36,"rate":12}},"runSound":"run","runSoundSpeed":333.3333333333333,"deadSound":"run","sex":2},
{"id":"hotgirl","head":{"x":6,"y":59},"chest":{"x":6,"y":24},"actions":{"wait":{"x":0.51,"y":0.36,"rate":10},"run":{"x":0.51,"y":0.36,"rate":24},"attack":{"x":0.51,"y":0.36,"rate":20,"a":4,"b":0},"magic":{"x":0.51,"y":0.36,"rate":15,"a":12,"b":0},"magic2":{"x":0.51,"y":0.36,"rate":20,"a":12,"b":0},"magic3":{"x":0.51,"y":0.36,"rate":20,"a":12,"b":0},"dead":{"x":0.51,"y":0.36,"rate":16},"faint":{"x":0.51,"y":0.36,"rate":15},"passive":{"x":0.51,"y":0.36,"rate":10,"a":7,"b":0},"win1":{"x":0.51,"y":0.36,"rate":12},"win2":{"x":0.51,"y":0.36,"rate":12}},"runSound":"run","runSoundSpeed":333.3333333333333,"deadSound":"run","sex":2},
{"id":"frogman","head":{"x":6,"y":59},"chest":{"x":6,"y":24},"actions":{"wait":{"x":0.51,"y":0.36,"rate":10},"run":{"x":0.51,"y":0.36,"rate":24},"attack":{"x":0.51,"y":0.36,"rate":20,"a":4,"b":0},"magic":{"x":0.51,"y":0.36,"rate":30,"a":10,"b":0},"magic2":{"x":0.51,"y":0.36,"rate":30,"a":10,"b":0},"magic3":{"x":0.51,"y":0.36,"rate":30,"a":10,"b":0},"dead":{"x":0.51,"y":0.36,"rate":16},"faint":{"x":0.51,"y":0.36,"rate":15},"passive":{"x":0.51,"y":0.36,"rate":15,"a":5,"b":0},"win1":{"x":0.51,"y":0.36,"rate":12},"win2":{"x":0.51,"y":0.36,"rate":12}},"runSound":"run","runSoundSpeed":333.3333333333333,"deadSound":"run","sex":1},
{"id":"laserman","head":{"x":6,"y":76},"chest":{"x":0,"y":27},"actions":{"wait":{"x":0.51,"y":0.36,"rate":10},"run":{"x":0.51,"y":0.36,"rate":24},"attack":{"x":0.51,"y":0.36,"rate":20,"a":4,"b":0},"magic":{"x":0.51,"y":0.36,"rate":15,"a":12,"b":0},"magic2":{"x":0.51,"y":0.36,"rate":20,"a":12,"b":0},"magic3":{"x":0.51,"y":0.36,"rate":20,"a":12,"b":0},"dead":{"x":0.51,"y":0.36,"rate":16},"faint":{"x":0.51,"y":0.36,"rate":15},"passive":{"x":0.51,"y":0.36,"rate":15,"a":5,"b":0},"win1":{"x":0.51,"y":0.36,"rate":12},"win2":{"x":0.51,"y":0.36,"rate":12}},"runSound":"run","runSoundSpeed":333.3333333333333,"deadSound":"run","sex":1},
{"id":"eagleman","head":{"x":6,"y":59},"chest":{"x":6,"y":24},"actions":{"wait":{"x":0.51,"y":0.36,"rate":10},"run":{"x":0.51,"y":0.36,"rate":24},"attack":{"x":0.51,"y":0.36,"rate":20,"a":6,"b":0},"magic":{"x":0.51,"y":0.36,"rate":15,"a":4,"b":0},"magic2":{"x":0.51,"y":0.36,"rate":20,"a":4,"b":0},"magic3":{"x":0.51,"y":0.36,"rate":20,"a":4,"b":0},"dead":{"x":0.51,"y":0.36,"rate":16},"faint":{"x":0.51,"y":0.36,"rate":15},"passive":{"x":0.51,"y":0.36,"rate":15,"a":7,"b":0},"win1":{"x":0.51,"y":0.36,"rate":12},"win2":{"x":0.51,"y":0.36,"rate":12}},"runSound":"run","runSoundSpeed":333.3333333333333,"deadSound":"run","sex":2},
{"id":"magicgirl","head":{"x":6,"y":59},"chest":{"x":6,"y":24},"actions":{"wait":{"x":0.51,"y":0.36,"rate":10},"run":{"x":0.51,"y":0.36,"rate":24},"attack":{"x":0.51,"y":0.36,"rate":18,"a":4,"b":0},"magic":{"x":0.51,"y":0.36,"rate":15,"a":9,"b":0},"magic2":{"x":0.51,"y":0.36,"rate":20,"a":9,"b":0},"magic3":{"x":0.51,"y":0.36,"rate":20,"a":9,"b":0},"dead":{"x":0.51,"y":0.36,"rate":16},"faint":{"x":0.51,"y":0.36,"rate":15},"passive":{"x":0.51,"y":0.36,"rate":15,"a":7,"b":0},"win1":{"x":0.51,"y":0.36,"rate":12},"win2":{"x":0.51,"y":0.36,"rate":12}},"runSound":"run","runSoundSpeed":333.3333333333333,"deadSound":"run","sex":2},
{"id":"bluegirl","head":{"x":6,"y":59},"chest":{"x":6,"y":24},"actions":{"wait":{"x":0.51,"y":0.36,"rate":10},"run":{"x":0.51,"y":0.36,"rate":24},"attack":{"x":0.51,"y":0.36,"rate":18,"a":5,"b":0},"magic":{"x":0.51,"y":0.36,"rate":15,"a":14,"b":0},"magic2":{"x":0.51,"y":0.36,"rate":20,"a":14,"b":0},"magic3":{"x":0.51,"y":0.36,"rate":20,"a":14,"b":0},"dead":{"x":0.51,"y":0.36,"rate":16},"faint":{"x":0.51,"y":0.36,"rate":15},"passive":{"x":0.51,"y":0.36,"rate":15,"a":7,"b":0},"win1":{"x":0.51,"y":0.36,"rate":12},"win2":{"x":0.51,"y":0.36,"rate":12}},"runSound":"run","runSoundSpeed":333.3333333333333,"deadSound":"run","sex":2},
{"id":"icegirl","head":{"x":6,"y":59},"chest":{"x":6,"y":24},"actions":{"wait":{"x":0.51,"y":0.36,"rate":10},"run":{"x":0.51,"y":0.36,"rate":24},"attack":{"x":0.51,"y":0.36,"rate":10,"a":4,"b":0},"magic":{"x":0.51,"y":0.36,"rate":15,"a":5,"b":0},"magic2":{"x":0.51,"y":0.36,"rate":20,"a":10,"b":0},"magic3":{"x":0.51,"y":0.36,"rate":20,"a":5,"b":0},"dead":{"x":0.51,"y":0.36,"rate":16},"faint":{"x":0.51,"y":0.36,"rate":15},"passive":{"x":0.51,"y":0.36,"rate":15,"a":7,"b":0},"win1":{"x":0.51,"y":0.36,"rate":12},"win2":{"x":0.51,"y":0.36,"rate":12}},"runSound":"run","runSoundSpeed":333.3333333333333,"deadSound":"run","sex":2},
{"id":"sarah","head":{"x":6,"y":59},"chest":{"x":6,"y":24},"actions":{"wait":{"x":0.51,"y":0.36,"rate":10},"run":{"x":0.51,"y":0.36,"rate":24},"attack":{"x":0.51,"y":0.36,"rate":18,"a":4,"b":0},"magic":{"x":0.51,"y":0.36,"rate":15,"a":9,"b":0},"magic2":{"x":0.51,"y":0.36,"rate":20,"a":9,"b":0},"magic3":{"x":0.51,"y":0.36,"rate":20,"a":9,"b":0},"dead":{"x":0.51,"y":0.36,"rate":16},"faint":{"x":0.51,"y":0.36,"rate":15},"passive":{"x":0.51,"y":0.36,"rate":15,"a":7,"b":0},"win1":{"x":0.51,"y":0.36,"rate":12},"win2":{"x":0.51,"y":0.36,"rate":12}},"runSound":"run","runSoundSpeed":333.3333333333333,"deadSound":"run","sex":2},
{"id":"nurse","head":{"x":6,"y":59},"chest":{"x":6,"y":24},"actions":{"wait":{"x":0.51,"y":0.36,"rate":10},"run":{"x":0.51,"y":0.36,"rate":24},"attack":{"x":0.51,"y":0.36,"rate":15,"a":2,"b":0},"magic":{"x":0.51,"y":0.36,"rate":15,"a":5,"b":0},"magic2":{"x":0.51,"y":0.36,"rate":20,"a":5,"b":0},"magic3":{"x":0.51,"y":0.36,"rate":20,"a":5,"b":0},"dead":{"x":0.51,"y":0.36,"rate":16},"faint":{"x":0.51,"y":0.36,"rate":15},"passive":{"x":0.51,"y":0.36,"rate":15,"a":7,"b":0},"win1":{"x":0.51,"y":0.36,"rate":12},"win2":{"x":0.51,"y":0.36,"rate":12}},"runSound":"run","runSoundSpeed":333.3333333333333,"deadSound":"run","sex":2},
{"id":"schoolgirl","head":{"x":6,"y":59},"chest":{"x":6,"y":24},"actions":{"wait":{"x":0.51,"y":0.36,"rate":10},"run":{"x":0.51,"y":0.36,"rate":24},"attack":{"x":0.51,"y":0.36,"rate":24,"a":2,"b":0},"magic":{"x":0.51,"y":0.36,"rate":15,"a":2,"b":0},"magic2":{"x":0.51,"y":0.36,"rate":20,"a":2,"b":0},"magic3":{"x":0.51,"y":0.36,"rate":20,"a":2,"b":0},"dead":{"x":0.51,"y":0.36,"rate":16},"faint":{"x":0.51,"y":0.36,"rate":15},"passive":{"x":0.51,"y":0.36,"rate":15,"a":7,"b":0},"win1":{"x":0.51,"y":0.36,"rate":12},"win2":{"x":0.51,"y":0.36,"rate":12}},"runSound":"run","runSoundSpeed":333.3333333333333,"deadSound":"run","sex":2},
{"id":"greengirl","head":{"x":6,"y":59},"chest":{"x":6,"y":24},"actions":{"wait":{"x":0.51,"y":0.36,"rate":10},"run":{"x":0.51,"y":0.36,"rate":24},"attack":{"x":0.51,"y":0.36,"rate":12,"a":2,"b":0},"magic":{"x":0.51,"y":0.36,"rate":15,"a":10,"b":0},"magic2":{"x":0.51,"y":0.36,"rate":20,"a":10,"b":0},"magic3":{"x":0.51,"y":0.36,"rate":20,"a":10,"b":0},"dead":{"x":0.51,"y":0.36,"rate":16},"faint":{"x":0.51,"y":0.36,"rate":15},"passive":{"x":0.51,"y":0.36,"rate":15,"a":7,"b":0},"win1":{"x":0.51,"y":0.36,"rate":12},"win2":{"x":0.51,"y":0.36,"rate":12}},"runSound":"run","runSoundSpeed":333.3333333333333,"deadSound":"run","sex":2},
{"id":"princess","head":{"x":6,"y":59},"chest":{"x":6,"y":24},"actions":{"wait":{"x":0.51,"y":0.36,"rate":10},"run":{"x":0.51,"y":0.36,"rate":24},"attack":{"x":0.51,"y":0.36,"rate":12,"a":2,"b":0},"magic":{"x":0.51,"y":0.36,"rate":15,"a":14,"b":0},"magic2":{"x":0.51,"y":0.36,"rate":20,"a":14,"b":0},"magic3":{"x":0.51,"y":0.36,"rate":20,"a":14,"b":0},"dead":{"x":0.51,"y":0.36,"rate":16},"faint":{"x":0.51,"y":0.36,"rate":15},"passive":{"x":0.51,"y":0.36,"rate":15,"a":7,"b":0},"win1":{"x":0.51,"y":0.36,"rate":12},"win2":{"x":0.51,"y":0.36,"rate":12}},"runSound":"run","runSoundSpeed":333.3333333333333,"deadSound":"run","sex":2},
{"id":"archer","head":{"x":0,"y":56},"chest":{"x":2,"y":18},"actions":{"wait":{"x":0.51,"y":0.36,"rate":10},"run":{"x":0.51,"y":0.36,"rate":10},"attack":{"x":0.51,"y":0.36,"rate":12,"a":2,"b":0},"magic":{"x":0.51,"y":0.36,"rate":12,"a":7,"b":0},"magic2":{"x":0.51,"y":0.36,"rate":12,"a":7,"b":0},"magic3":{"x":0.51,"y":0.36,"rate":20,"a":14,"b":0},"dead":{"x":0.51,"y":0.36,"rate":10},"faint":{"x":0.51,"y":0.36,"rate":12},"passive":{"x":0.51,"y":0.36,"rate":12,"a":7,"b":0},"win1":{"x":0.51,"y":0.36,"rate":12},"win2":{"x":0.51,"y":0.36,"rate":12}},"runSound":"run","runSoundSpeed":400,"deadSound":"fuleiya04","sex":0},
{"id":"dog","head":{"x":0,"y":101},"chest":{"x":-1,"y":44},"actions":{"wait":{"x":0.51,"y":0.36,"rate":10},"run":{"x":0.51,"y":0.36,"rate":10},"attack":{"x":0.51,"y":0.36,"rate":8,"a":2,"b":0},"magic":{"x":0.51,"y":0.36,"rate":8,"a":4,"b":0},"magic2":{"x":0.51,"y":0.36,"rate":8,"a":4,"b":0},"magic3":{"x":0.51,"y":0.36,"rate":8,"a":3,"b":0},"dead":{"x":0.51,"y":0.36,"rate":8},"faint":{"x":0.51,"y":0.36,"rate":8},"passive":{"x":0.51,"y":0.36,"rate":8,"a":7,"b":0},"win1":{"x":0.51,"y":0.36,"rate":8},"win2":{"x":0.51,"y":0.36,"rate":8}},"runSound":"run","runSoundSpeed":400,"deadSound":"ranshaoshouren01","sex":0},
{"id":"dragon","head":{"x":0,"y":64},"chest":{"x":4,"y":28},"actions":{"wait":{"x":0.51,"y":0.36,"rate":10},"run":{"x":0.51,"y":0.36,"rate":10},"attack":{"x":0.51,"y":0.36,"rate":10,"a":2,"b":0},"magic":{"x":0.51,"y":0.36,"rate":10,"a":4,"b":0},"magic2":{"x":0.51,"y":0.36,"rate":10,"a":2,"b":0},"magic3":{"x":0.51,"y":0.36,"rate":20,"a":13,"b":0},"dead":{"x":0.51,"y":0.36,"rate":10},"faint":{"x":0.51,"y":0.36,"rate":12},"passive":{"x":0.51,"y":0.36,"rate":12,"a":7,"b":0},"win1":{"x":0.51,"y":0.36,"rate":12},"win2":{"x":0.51,"y":0.36,"rate":12}},"runSound":"run","runSoundSpeed":600,"deadSound":"xiyigongzhu01","sex":0},
{"id":"fuleiya","head":{"x":0,"y":157},"chest":{"x":1,"y":74},"actions":{"wait":{"x":0.51,"y":0.22,"rate":10},"run":{"x":0.51,"y":0.22,"rate":10},"attack":{"x":0.51,"y":0.22,"rate":10,"a":2,"b":0},"magic":{"x":0.51,"y":0.22,"rate":12,"a":1,"b":0},"magic2":{"x":0.51,"y":0.22,"rate":10,"a":6,"b":0},"magic3":{"x":0.51,"y":0.22,"rate":20,"a":13,"b":0},"dead":{"x":0.51,"y":0.22,"rate":10},"faint":{"x":0.51,"y":0.22,"rate":12},"passive":{"x":0.51,"y":0.22,"rate":12,"a":7,"b":0},"win1":{"x":0.51,"y":0.22,"rate":12},"win2":{"x":0.51,"y":0.22,"rate":12}},"runSound":"run","runSoundSpeed":500,"deadSound":"daheilong01","sex":0},
{"id":"hell","head":{"x":0,"y":112},"chest":{"x":5,"y":40},"actions":{"wait":{"x":0.51,"y":0.36,"rate":10},"run":{"x":0.51,"y":0.36,"rate":10},"attack":{"x":0.51,"y":0.36,"rate":12,"a":2,"b":0},"magic":{"x":0.51,"y":0.36,"rate":12,"a":4,"b":0},"magic2":{"x":0.51,"y":0.36,"rate":12,"a":7,"b":0},"magic3":{"x":0.51,"y":0.36,"rate":12,"a":3,"b":0},"dead":{"x":0.51,"y":0.36,"rate":12},"faint":{"x":0.51,"y":0.36,"rate":12},"passive":{"x":0.51,"y":0.36,"rate":12,"a":7,"b":0},"win1":{"x":0.51,"y":0.36,"rate":12},"win2":{"x":0.51,"y":0.36,"rate":12}},"runSound":"run","runSoundSpeed":600,"deadSound":"chonghou01","sex":0},
{"id":"mage","head":{"x":0,"y":104},"chest":{"x":7,"y":49},"actions":{"wait":{"x":0.51,"y":0.36,"rate":10},"run":{"x":0.51,"y":0.36,"rate":10},"attack":{"x":0.51,"y":0.36,"rate":12,"a":2,"b":0},"magic":{"x":0.51,"y":0.36,"rate":12,"a":4,"b":0},"magic2":{"x":0.51,"y":0.36,"rate":12,"a":10,"b":0},"magic3":{"x":0.51,"y":0.36,"rate":20,"a":13,"b":0},"dead":{"x":0.51,"y":0.36,"rate":12},"faint":{"x":0.51,"y":0.36,"rate":12},"passive":{"x":0.51,"y":0.36,"rate":12,"a":7,"b":0},"win1":{"x":0.51,"y":0.36,"rate":12},"win2":{"x":0.51,"y":0.36,"rate":12}},"runSound":"run","runSoundSpeed":800,"deadSound":"lieyanmowang01","sex":0},
{"id":"incest","head":{"x":0,"y":92},"chest":{"x":11,"y":34},"actions":{"wait":{"x":0.51,"y":0.36,"rate":10},"run":{"x":0.51,"y":0.36,"rate":10},"attack":{"x":0.51,"y":0.36,"rate":10,"a":2,"b":0},"magic":{"x":0.51,"y":0.36,"rate":12,"a":4,"b":0},"magic2":{"x":0.51,"y":0.36,"rate":12,"a":12,"b":0},"magic3":{"x":0.51,"y":0.36,"rate":20,"a":13,"b":0},"dead":{"x":0.51,"y":0.36,"rate":12},"faint":{"x":0.51,"y":0.36,"rate":12},"passive":{"x":0.51,"y":0.36,"rate":12,"a":7,"b":0},"win1":{"x":0.51,"y":0.36,"rate":12},"win2":{"x":0.51,"y":0.36,"rate":12}},"runSound":"run","runSoundSpeed":600,"deadSound":"damofashi01","sex":0},
{"id":"orcburn","head":{"x":0,"y":81},"chest":{"x":5,"y":28},"actions":{"wait":{"x":0.51,"y":0.36,"rate":10},"run":{"x":0.51,"y":0.36,"rate":10},"attack":{"x":0.51,"y":0.36,"rate":12,"a":2,"b":0},"magic":{"x":0.51,"y":0.36,"rate":12,"a":11,"b":0},"magic2":{"x":0.51,"y":0.36,"rate":12,"a":9,"b":0},"magic3":{"x":0.51,"y":0.36,"rate":20,"a":13,"b":0},"dead":{"x":0.51,"y":0.36,"rate":12},"faint":{"x":0.51,"y":0.36,"rate":12},"passive":{"x":0.51,"y":0.36,"rate":12,"a":7,"b":0},"win1":{"x":0.51,"y":0.36,"rate":12},"win2":{"x":0.51,"y":0.36,"rate":12}},"runSound":"run","runSoundSpeed":600,"deadSound":"liehsounvyao01","sex":0},
{"id":"lizard","head":{"x":16,"y":70},"chest":{"x":2,"y":25},"actions":{"wait":{"x":0.46,"y":0.36,"rate":10},"run":{"x":0.46,"y":0.36,"rate":10},"attack":{"x":0.51,"y":0.36,"rate":12,"a":2,"b":0},"magic":{"x":0.46,"y":0.36,"rate":10,"a":4,"b":0},"magic2":{"x":0.46,"y":0.36,"rate":10,"a":3,"b":0},"magic3":{"x":0.51,"y":0.36,"rate":12,"a":6,"b":0},"dead":{"x":0.51,"y":0.36,"rate":10},"faint":{"x":0.51,"y":0.36,"rate":12},"passive":{"x":0.51,"y":0.36,"rate":12,"a":7,"b":0},"win1":{"x":0.51,"y":0.36,"rate":12},"win2":{"x":0.51,"y":0.36,"rate":12}},"runSound":"run","runSoundSpeed":600,"deadSound":"youlinggongzhu01","sex":0},
{"id":"axe","head":{"x":0,"y":84},"chest":{"x":0,"y":20},"actions":{"wait":{"x":0.51,"y":0.36,"rate":10},"run":{"x":0.51,"y":0.36,"rate":10},"attack":{"x":0.51,"y":0.36,"rate":12,"a":5,"b":0},"magic":{"x":0.46,"y":0.36,"rate":10,"a":7,"b":0},"magic2":{"x":0.46,"y":0.36,"rate":10,"a":4,"b":0},"magic3":{"x":0.51,"y":0.36,"rate":12,"a":8,"b":0},"dead":{"x":0.51,"y":0.36,"rate":10},"faint":{"x":0.51,"y":0.36,"rate":12},"passive":{"x":0.51,"y":0.36,"rate":12,"a":7,"b":0},"win1":{"x":0.51,"y":0.36,"rate":12},"win2":{"x":0.51,"y":0.36,"rate":12}},"runSound":"","runSoundSpeed":0,"deadSound":"","sex":0},
{"id":"bat","head":{"x":0,"y":60},"chest":{"x":5,"y":26},"actions":{"wait":{"x":0.46,"y":0.3,"rate":10},"run":{"x":0.51,"y":0.3,"rate":10},"attack":{"x":0.46,"y":0.3,"rate":5,"a":1,"b":0},"magic":{"x":0.46,"y":0.3,"rate":10,"a":7,"b":0},"magic2":{"x":0.46,"y":0.3,"rate":10,"a":4,"b":0},"magic3":{"x":0.51,"y":0.3,"rate":12,"a":8,"b":0},"dead":{"x":0.46,"y":0.3,"rate":10},"faint":{"x":0.46,"y":0.3,"rate":12},"passive":{"x":0.46,"y":0.3,"rate":12,"a":7,"b":0},"win1":{"x":0.46,"y":0.3,"rate":12},"win2":{"x":0.46,"y":0.3,"rate":12}},"runSound":"run","runSoundSpeed":400,"deadSound":"run","sex":0},
{"id":"bear","head":{"x":0,"y":84},"chest":{"x":4,"y":28},"actions":{"wait":{"x":0.51,"y":0.36,"rate":10},"run":{"x":0.51,"y":0.36,"rate":10},"attack":{"x":0.51,"y":0.36,"rate":10,"a":3,"b":0},"magic":{"x":0.46,"y":0.36,"rate":10,"a":7,"b":0},"magic2":{"x":0.46,"y":0.36,"rate":10,"a":4,"b":0},"magic3":{"x":0.51,"y":0.36,"rate":12,"a":8,"b":0},"dead":{"x":0.51,"y":0.36,"rate":10},"faint":{"x":0.51,"y":0.36,"rate":12},"passive":{"x":0.51,"y":0.36,"rate":12,"a":7,"b":0},"win1":{"x":0.51,"y":0.36,"rate":12},"win2":{"x":0.51,"y":0.36,"rate":12}},"runSound":"run","runSoundSpeed":800,"deadSound":"run","sex":0},
{"id":"crawl","head":{"x":0,"y":84},"chest":{"x":4,"y":28},"actions":{"wait":{"x":0.51,"y":0.36,"rate":10},"run":{"x":0.51,"y":0.36,"rate":10},"attack":{"x":0.51,"y":0.36,"rate":10,"a":3,"b":0},"magic":{"x":0.46,"y":0.36,"rate":10,"a":7,"b":0},"magic2":{"x":0.46,"y":0.36,"rate":10,"a":4,"b":0},"magic3":{"x":0.51,"y":0.36,"rate":12,"a":8,"b":0},"dead":{"x":0.51,"y":0.36,"rate":10},"faint":{"x":0.51,"y":0.36,"rate":12},"passive":{"x":0.51,"y":0.36,"rate":12,"a":7,"b":0},"win1":{"x":0.51,"y":0.36,"rate":12},"win2":{"x":0.51,"y":0.36,"rate":12}},"runSound":"run","runSoundSpeed":800,"deadSound":"run","sex":0},
{"id":"deer","head":{"x":0,"y":63},"chest":{"x":7,"y":23},"actions":{"wait":{"x":0.51,"y":0.36,"rate":10},"run":{"x":0.51,"y":0.36,"rate":10},"attack":{"x":0.51,"y":0.36,"rate":12,"a":3,"b":0},"magic":{"x":0.46,"y":0.36,"rate":10,"a":7,"b":0},"magic2":{"x":0.46,"y":0.36,"rate":10,"a":4,"b":0},"magic3":{"x":0.51,"y":0.36,"rate":12,"a":8,"b":0},"dead":{"x":0.51,"y":0.36,"rate":12},"faint":{"x":0.51,"y":0.36,"rate":12},"passive":{"x":0.51,"y":0.36,"rate":12,"a":7,"b":0},"win1":{"x":0.51,"y":0.36,"rate":12},"win2":{"x":0.51,"y":0.36,"rate":12}},"runSound":"run","runSoundSpeed":500,"deadSound":"run","sex":0},
{"id":"deerrider","head":{"x":0,"y":95},"chest":{"x":7,"y":43},"actions":{"wait":{"x":0.51,"y":0.36,"rate":10},"run":{"x":0.51,"y":0.36,"rate":10},"attack":{"x":0.51,"y":0.36,"rate":12,"a":9,"b":0},"magic":{"x":0.46,"y":0.36,"rate":10,"a":7,"b":0},"magic2":{"x":0.46,"y":0.36,"rate":10,"a":4,"b":0},"magic3":{"x":0.51,"y":0.36,"rate":12,"a":8,"b":0},"dead":{"x":0.51,"y":0.36,"rate":12},"faint":{"x":0.51,"y":0.36,"rate":12},"passive":{"x":0.51,"y":0.36,"rate":12,"a":7,"b":0},"win1":{"x":0.51,"y":0.36,"rate":12},"win2":{"x":0.51,"y":0.36,"rate":12}},"runSound":"run","runSoundSpeed":500,"deadSound":"run","sex":0},
{"id":"dragonfly","head":{"x":0,"y":80},"chest":{"x":0,"y":35},"actions":{"wait":{"x":0.51,"y":0.3,"rate":10},"run":{"x":0.51,"y":0.3,"rate":10},"attack":{"x":0.51,"y":0.3,"rate":10,"a":2,"b":0},"magic":{"x":0.46,"y":0.3,"rate":10,"a":7,"b":0},"magic2":{"x":0.46,"y":0.3,"rate":10,"a":4,"b":0},"magic3":{"x":0.51,"y":0.3,"rate":12,"a":8,"b":0},"dead":{"x":0.51,"y":0.3,"rate":12},"faint":{"x":0.51,"y":0.3,"rate":12},"passive":{"x":0.51,"y":0.3,"rate":12,"a":7,"b":0},"win1":{"x":0.51,"y":0.3,"rate":12},"win2":{"x":0.51,"y":0.3,"rate":12}},"runSound":"run","runSoundSpeed":300,"deadSound":"run","sex":0},
{"id":"fashi","head":{"x":0,"y":111},"chest":{"x":0,"y":36},"actions":{"wait":{"x":0.51,"y":0.36,"rate":10},"run":{"x":0.51,"y":0.36,"rate":10},"attack":{"x":0.51,"y":0.36,"rate":12,"a":3,"b":0},"magic":{"x":0.46,"y":0.36,"rate":10,"a":7,"b":0},"magic2":{"x":0.46,"y":0.36,"rate":10,"a":4,"b":0},"magic3":{"x":0.51,"y":0.36,"rate":12,"a":8,"b":0},"dead":{"x":0.51,"y":0.36,"rate":12},"faint":{"x":0.51,"y":0.36,"rate":12},"passive":{"x":0.51,"y":0.36,"rate":12,"a":7,"b":0},"win1":{"x":0.51,"y":0.36,"rate":12},"win2":{"x":0.51,"y":0.36,"rate":12}},"runSound":"run","runSoundSpeed":800,"deadSound":"run","sex":0},
{"id":"griffin","head":{"x":0,"y":88},"chest":{"x":5,"y":36},"actions":{"wait":{"x":0.51,"y":0.3,"rate":10},"run":{"x":0.51,"y":0.3,"rate":10},"attack":{"x":0.51,"y":0.3,"rate":12,"a":3,"b":0},"magic":{"x":0.46,"y":0.3,"rate":10,"a":7,"b":0},"magic2":{"x":0.46,"y":0.3,"rate":10,"a":4,"b":0},"magic3":{"x":0.51,"y":0.3,"rate":12,"a":8,"b":0},"dead":{"x":0.51,"y":0.3,"rate":12},"faint":{"x":0.51,"y":0.3,"rate":12},"passive":{"x":0.51,"y":0.3,"rate":12,"a":7,"b":0},"win1":{"x":0.51,"y":0.3,"rate":12},"win2":{"x":0.51,"y":0.3,"rate":12}},"runSound":"run","runSoundSpeed":800,"deadSound":"run","sex":0},
{"id":"mashroom","head":{"x":0,"y":88},"chest":{"x":0,"y":33},"actions":{"wait":{"x":0.51,"y":0.36,"rate":10},"run":{"x":0.51,"y":0.36,"rate":10},"attack":{"x":0.51,"y":0.36,"rate":10,"a":3,"b":0},"magic":{"x":0.46,"y":0.36,"rate":10,"a":7,"b":0},"magic2":{"x":0.46,"y":0.36,"rate":10,"a":4,"b":0},"magic3":{"x":0.51,"y":0.36,"rate":12,"a":8,"b":0},"dead":{"x":0.51,"y":0.36,"rate":12},"faint":{"x":0.51,"y":0.36,"rate":12},"passive":{"x":0.51,"y":0.36,"rate":12,"a":7,"b":0},"win1":{"x":0.51,"y":0.36,"rate":12},"win2":{"x":0.51,"y":0.36,"rate":12}},"runSound":"run","runSoundSpeed":400,"deadSound":"run","sex":0},
{"id":"orcblade","head":{"x":0,"y":76},"chest":{"x":0,"y":27},"actions":{"wait":{"x":0.51,"y":0.36,"rate":10},"run":{"x":0.51,"y":0.36,"rate":10},"attack":{"x":0.51,"y":0.36,"rate":12,"a":4,"b":0},"magic":{"x":0.46,"y":0.36,"rate":10,"a":7,"b":0},"magic2":{"x":0.46,"y":0.36,"rate":10,"a":4,"b":0},"magic3":{"x":0.51,"y":0.36,"rate":12,"a":8,"b":0},"dead":{"x":0.51,"y":0.36,"rate":12},"faint":{"x":0.51,"y":0.36,"rate":12},"passive":{"x":0.51,"y":0.36,"rate":12,"a":7,"b":0},"win1":{"x":0.51,"y":0.36,"rate":12},"win2":{"x":0.51,"y":0.36,"rate":12}},"runSound":"run","runSoundSpeed":800,"deadSound":"run","sex":0},
{"id":"rock","head":{"x":0,"y":85},"chest":{"x":3,"y":33},"actions":{"wait":{"x":0.51,"y":0.36,"rate":10},"run":{"x":0.51,"y":0.36,"rate":10},"attack":{"x":0.51,"y":0.36,"rate":12,"a":5,"b":0},"magic":{"x":0.46,"y":0.36,"rate":10,"a":7,"b":0},"magic2":{"x":0.46,"y":0.36,"rate":10,"a":4,"b":0},"magic3":{"x":0.51,"y":0.36,"rate":12,"a":8,"b":0},"dead":{"x":0.51,"y":0.36,"rate":12},"faint":{"x":0.51,"y":0.36,"rate":12},"passive":{"x":0.51,"y":0.36,"rate":12,"a":7,"b":0},"win1":{"x":0.51,"y":0.36,"rate":12},"win2":{"x":0.51,"y":0.36,"rate":12}},"runSound":"run","runSoundSpeed":800,"deadSound":"run","sex":0},
{"id":"tiger","head":{"x":0,"y":112},"chest":{"x":0,"y":56},"actions":{"wait":{"x":0.51,"y":0.36,"rate":10},"run":{"x":0.51,"y":0.36,"rate":12},"attack":{"x":0.51,"y":0.36,"rate":12,"a":3,"b":0},"magic":{"x":0.46,"y":0.36,"rate":10,"a":7,"b":0},"magic2":{"x":0.46,"y":0.36,"rate":10,"a":4,"b":0},"magic3":{"x":0.51,"y":0.36,"rate":12,"a":8,"b":0},"dead":{"x":0.51,"y":0.36,"rate":12},"faint":{"x":0.51,"y":0.36,"rate":12},"passive":{"x":0.51,"y":0.36,"rate":12,"a":7,"b":0},"win1":{"x":0.51,"y":0.36,"rate":12},"win2":{"x":0.51,"y":0.36,"rate":12}},"runSound":"run","runSoundSpeed":666.6666666666666,"deadSound":"run","sex":0},
{"id":"wasp","head":{"x":0,"y":77},"chest":{"x":0,"y":38},"actions":{"wait":{"x":0.53,"y":0.3,"rate":10},"run":{"x":0.51,"y":0.3,"rate":12},"attack":{"x":0.53,"y":0.3,"rate":10,"a":2,"b":0},"magic":{"x":0.46,"y":0.3,"rate":10,"a":7,"b":0},"magic2":{"x":0.46,"y":0.3,"rate":10,"a":4,"b":0},"magic3":{"x":0.51,"y":0.3,"rate":12,"a":8,"b":0},"dead":{"x":0.53,"y":0.3,"rate":12},"faint":{"x":0.53,"y":0.3,"rate":12},"passive":{"x":0.53,"y":0.3,"rate":12,"a":7,"b":0},"win1":{"x":0.53,"y":0.3,"rate":12},"win2":{"x":0.53,"y":0.3,"rate":12}},"runSound":"run","runSoundSpeed":666.6666666666666,"deadSound":"run","sex":0},
{"id":"spear","head":{"x":0,"y":81},"chest":{"x":0,"y":25},"actions":{"wait":{"x":0.51,"y":0.36,"rate":10},"run":{"x":0.51,"y":0.36,"rate":10},"attack":{"x":0.51,"y":0.36,"rate":12,"a":3,"b":0},"magic":{"x":0.46,"y":0.36,"rate":10,"a":7,"b":0},"magic2":{"x":0.46,"y":0.36,"rate":10,"a":4,"b":0},"magic3":{"x":0.51,"y":0.36,"rate":12,"a":8,"b":0},"dead":{"x":0.51,"y":0.36,"rate":12},"faint":{"x":0.51,"y":0.36,"rate":12},"passive":{"x":0.51,"y":0.36,"rate":12,"a":7,"b":0},"win1":{"x":0.51,"y":0.36,"rate":12},"win2":{"x":0.51,"y":0.36,"rate":12}},"runSound":"run","runSoundSpeed":400,"deadSound":"run","sex":0},
{"id":"snail","head":{"x":0,"y":78},"chest":{"x":4,"y":26},"actions":{"wait":{"x":0.51,"y":0.36,"rate":10},"run":{"x":0.51,"y":0.36,"rate":10},"attack":{"x":0.51,"y":0.36,"rate":12,"a":7,"b":0},"magic":{"x":0.46,"y":0.36,"rate":10,"a":7,"b":0},"magic2":{"x":0.46,"y":0.36,"rate":10,"a":4,"b":0},"magic3":{"x":0.51,"y":0.36,"rate":12,"a":8,"b":0},"dead":{"x":0.51,"y":0.36,"rate":12},"faint":{"x":0.51,"y":0.36,"rate":12},"passive":{"x":0.51,"y":0.36,"rate":12,"a":7,"b":0},"win1":{"x":0.51,"y":0.36,"rate":12},"win2":{"x":0.51,"y":0.36,"rate":12}},"runSound":"run","runSoundSpeed":400,"deadSound":"run","sex":0},
{"id":"mob","head":{"x":0,"y":55},"chest":{"x":0,"y":19},"actions":{"wait":{"x":0.48,"y":0.22,"rate":10},"run":{"x":0.48,"y":0.22,"rate":10},"attack":{"x":0.48,"y":0.22,"rate":10,"a":3,"b":0},"magic":{"x":0.48,"y":0.22,"rate":10,"a":4,"b":0},"magic2":{"x":0.48,"y":0.22,"rate":10,"a":4,"b":0},"magic3":{"x":0.48,"y":0.22,"rate":10,"a":4,"b":0},"dead":{"x":0.48,"y":0.22,"rate":10},"faint":{"x":0.48,"y":0.22,"rate":10},"passive":{"x":0.48,"y":0.22,"rate":10,"a":4,"b":0},"win1":{"x":0.48,"y":0.22,"rate":10},"win2":{"x":0.48,"y":0.22,"rate":10}},"runSound":"run","runSoundSpeed":500,"deadSound":"run","sex":0},
{"id":"spirit","head":{"x":0,"y":63},"chest":{"x":0,"y":20},"actions":{"wait":{"x":0.51,"y":0.36,"rate":10},"run":{"x":0.51,"y":0.36,"rate":10},"attack":{"x":0.51,"y":0.36,"rate":12,"a":4,"b":0},"magic":{"x":0.46,"y":0.36,"rate":10,"a":7,"b":0},"magic2":{"x":0.46,"y":0.36,"rate":10,"a":4,"b":0},"magic3":{"x":0.51,"y":0.36,"rate":12,"a":8,"b":0},"dead":{"x":0.51,"y":0.36,"rate":12},"faint":{"x":0.51,"y":0.36,"rate":12},"passive":{"x":0.51,"y":0.36,"rate":12,"a":7,"b":0},"win1":{"x":0.51,"y":0.36,"rate":12},"win2":{"x":0.51,"y":0.36,"rate":12}},"runSound":"","runSoundSpeed":0,"deadSound":"","sex":0},
{"id":"wolf","head":{"x":0,"y":79},"chest":{"x":0,"y":29},"actions":{"wait":{"x":0.51,"y":0.36,"rate":5},"run":{"x":0.51,"y":0.36,"rate":10},"attack":{"x":0.51,"y":0.36,"rate":12,"a":3,"b":0},"magic":{"x":0.46,"y":0.36,"rate":10,"a":7,"b":0},"magic2":{"x":0.46,"y":0.36,"rate":10,"a":4,"b":0},"magic3":{"x":0.51,"y":0.36,"rate":12,"a":8,"b":0},"dead":{"x":0.51,"y":0.36,"rate":12},"faint":{"x":0.51,"y":0.36,"rate":12},"passive":{"x":0.51,"y":0.36,"rate":12,"a":7,"b":0},"win1":{"x":0.51,"y":0.36,"rate":12},"win2":{"x":0.51,"y":0.36,"rate":12}},"runSound":"run","runSoundSpeed":400,"deadSound":"run","sex":0},
{"id":"snowman","head":{"x":0,"y":64},"chest":{"x":-2,"y":20},"actions":{"wait":{"x":0.51,"y":0.36,"rate":10},"run":{"x":0.51,"y":0.36,"rate":10},"attack":{"x":0.51,"y":0.36,"rate":12,"a":4,"b":0},"magic":{"x":0.46,"y":0.36,"rate":10,"a":7,"b":0},"magic2":{"x":0.46,"y":0.36,"rate":10,"a":4,"b":0},"magic3":{"x":0.51,"y":0.36,"rate":12,"a":8,"b":0},"dead":{"x":0.51,"y":0.36,"rate":12},"faint":{"x":0.51,"y":0.36,"rate":12},"passive":{"x":0.51,"y":0.36,"rate":12,"a":7,"b":0},"win1":{"x":0.51,"y":0.36,"rate":12},"win2":{"x":0.51,"y":0.36,"rate":12}},"runSound":"run","runSoundSpeed":400,"deadSound":"run","sex":0},
{"id":"snake","head":{"x":0,"y":61},"chest":{"x":5,"y":20},"actions":{"wait":{"x":0.51,"y":0.36,"rate":10},"run":{"x":0.51,"y":0.36,"rate":12},"attack":{"x":0.51,"y":0.36,"rate":12,"a":4,"b":0},"magic":{"x":0.46,"y":0.36,"rate":10,"a":7,"b":0},"magic2":{"x":0.46,"y":0.36,"rate":10,"a":4,"b":0},"magic3":{"x":0.51,"y":0.36,"rate":12,"a":8,"b":0},"dead":{"x":0.51,"y":0.36,"rate":12},"faint":{"x":0.51,"y":0.36,"rate":12},"passive":{"x":0.51,"y":0.36,"rate":12,"a":7,"b":0},"win1":{"x":0.51,"y":0.36,"rate":12},"win2":{"x":0.51,"y":0.36,"rate":12}},"runSound":"run","runSoundSpeed":666.6666666666666,"deadSound":"run","sex":0},
{"id":"orcwizzard","head":{"x":0,"y":79},"chest":{"x":0,"y":27},"actions":{"wait":{"x":0.51,"y":0.36,"rate":5},"run":{"x":0.51,"y":0.36,"rate":12},"attack":{"x":0.51,"y":0.36,"rate":12,"a":4,"b":0},"magic":{"x":0.46,"y":0.36,"rate":10,"a":7,"b":0},"magic2":{"x":0.46,"y":0.36,"rate":10,"a":4,"b":0},"magic3":{"x":0.51,"y":0.36,"rate":12,"a":8,"b":0},"dead":{"x":0.51,"y":0.36,"rate":12},"faint":{"x":0.51,"y":0.36,"rate":12},"passive":{"x":0.51,"y":0.36,"rate":12,"a":7,"b":0},"win1":{"x":0.51,"y":0.36,"rate":12},"win2":{"x":0.51,"y":0.36,"rate":12}},"runSound":"run","runSoundSpeed":666.6666666666666,"deadSound":"run","sex":0},
{"id":"cannibal","head":{"x":0,"y":79},"chest":{"x":0,"y":31},"actions":{"wait":{"x":0.51,"y":0.36,"rate":5},"run":{"x":0.51,"y":0.36,"rate":12},"attack":{"x":0.51,"y":0.36,"rate":12,"a":2,"b":0},"magic":{"x":0.46,"y":0.36,"rate":10,"a":7,"b":0},"magic2":{"x":0.46,"y":0.36,"rate":10,"a":4,"b":0},"magic3":{"x":0.51,"y":0.36,"rate":12,"a":8,"b":0},"dead":{"x":0.51,"y":0.36,"rate":12},"faint":{"x":0.51,"y":0.36,"rate":12},"passive":{"x":0.51,"y":0.36,"rate":12,"a":7,"b":0},"win1":{"x":0.51,"y":0.36,"rate":12},"win2":{"x":0.51,"y":0.36,"rate":12}},"runSound":"run","runSoundSpeed":583.3333333333334,"deadSound":"run","sex":0},
{"id":"wizzard","head":{"x":0,"y":100},"chest":{"x":-1,"y":35},"actions":{"wait":{"x":0.51,"y":0.3,"rate":10},"run":{"x":0.51,"y":0.3,"rate":10},"attack":{"x":0.51,"y":0.3,"rate":12,"a":4,"b":0},"magic":{"x":0.46,"y":0.3,"rate":10,"a":7,"b":0},"magic2":{"x":0.46,"y":0.3,"rate":10,"a":4,"b":0},"magic3":{"x":0.51,"y":0.3,"rate":12,"a":8,"b":0},"dead":{"x":0.51,"y":0.3,"rate":10},"faint":{"x":0.51,"y":0.3,"rate":12},"passive":{"x":0.51,"y":0.3,"rate":12,"a":7,"b":0},"win1":{"x":0.51,"y":0.3,"rate":12},"win2":{"x":0.51,"y":0.3,"rate":12}},"runSound":"run","runSoundSpeed":300,"deadSound":"run","sex":0},
{"id":"orcarcher","head":{"x":0,"y":79},"chest":{"x":0,"y":26},"actions":{"wait":{"x":0.51,"y":0.36,"rate":10},"run":{"x":0.51,"y":0.36,"rate":10},"attack":{"x":0.51,"y":0.36,"rate":12,"a":4,"b":0},"magic":{"x":0.46,"y":0.36,"rate":10,"a":7,"b":0},"magic2":{"x":0.46,"y":0.36,"rate":10,"a":4,"b":0},"magic3":{"x":0.51,"y":0.36,"rate":12,"a":8,"b":0},"dead":{"x":0.51,"y":0.36,"rate":12},"faint":{"x":0.51,"y":0.36,"rate":12},"passive":{"x":0.51,"y":0.36,"rate":12,"a":7,"b":0},"win1":{"x":0.51,"y":0.36,"rate":12},"win2":{"x":0.51,"y":0.36,"rate":12}},"runSound":"run","runSoundSpeed":400,"deadSound":"run","sex":0},
{"id":"worm","head":{"x":0,"y":73},"chest":{"x":0,"y":29},"actions":{"wait":{"x":0.51,"y":0.36,"rate":5},"run":{"x":0.51,"y":0.36,"rate":10},"attack":{"x":0.51,"y":0.36,"rate":10,"a":3,"b":0},"magic":{"x":0.46,"y":0.36,"rate":10,"a":7,"b":0},"magic2":{"x":0.46,"y":0.36,"rate":10,"a":4,"b":0},"magic3":{"x":0.51,"y":0.36,"rate":12,"a":8,"b":0},"dead":{"x":0.51,"y":0.36,"rate":12},"faint":{"x":0.51,"y":0.36,"rate":12},"passive":{"x":0.51,"y":0.36,"rate":12,"a":7,"b":0},"win1":{"x":0.51,"y":0.36,"rate":12},"win2":{"x":0.51,"y":0.36,"rate":12}},"runSound":"run","runSoundSpeed":400,"deadSound":"run","sex":0},
{"id":"zhiliaohua","head":{"x":0,"y":79},"chest":{"x":0,"y":31},"actions":{"wait":{"x":0.51,"y":0.36,"rate":5},"run":{"x":0.51,"y":0.36,"rate":12},"attack":{"x":0.51,"y":0.36,"rate":12,"a":2,"b":0},"magic":{"x":0.46,"y":0.36,"rate":10,"a":7,"b":0},"magic2":{"x":0.46,"y":0.36,"rate":10,"a":4,"b":0},"magic3":{"x":0.51,"y":0.36,"rate":12,"a":8,"b":0},"dead":{"x":0.51,"y":0.36,"rate":12},"faint":{"x":0.51,"y":0.36,"rate":12},"passive":{"x":0.51,"y":0.36,"rate":12,"a":7,"b":0},"win1":{"x":0.51,"y":0.36,"rate":12},"win2":{"x":0.51,"y":0.36,"rate":12}},"runSound":"run","runSoundSpeed":583.3333333333334,"deadSound":"run","sex":0}
]